mediapills/__init__.py
mediapills/http_foundation/__init__.py
mediapills/http_foundation/requests.py
mediapills/http_foundation/responses.py
mediapills.http_foundation-0.0.1.dist-info/LICENSE.md
mediapills.http_foundation-0.0.1.dist-info/METADATA
mediapills.http_foundation-0.0.1.dist-info/WHEEL
mediapills.http_foundation-0.0.1.dist-info/top_level.txt
mediapills.http_foundation-0.0.1.dist-info/zip-safe
mediapills.http_foundation-0.0.1.dist-info/RECORD
