Metadata-Version: 2.1
Name: mediapills.http-foundation
Version: 0.0.1
Summary: Object-oriented layer for the HTTP specification
Home-page: https://github.com/mediapills/http-foundation.git
Author: Andriy Yatskovets
Author-email: andriy.yatskovets@gmail.com
License: 'MIT'
Project-URL: Bug Tracker, https://github.com/mediapills/http-foundation/issues
Project-URL: Source Code, https://github.com/mediapills/http-foundation
Keywords: 'HTTP','mediapills'
Platform: 'any'
Classifier: Development Status :: 1 - Planning
Classifier: Intended Audience :: Developers
Classifier: Intended Audience :: Education
Classifier: License :: OSI Approved :: MIT License
Classifier: Programming Language :: Python
Classifier: Programming Language :: Python :: 3 :: Only
Classifier: Programming Language :: Python :: 3.6
Classifier: Programming Language :: Python :: 3.7
Classifier: Programming Language :: Python :: 3.8
Classifier: Programming Language :: Python :: 3.9
Classifier: Programming Language :: Python :: Implementation
Classifier: Programming Language :: Python :: Implementation :: PyPy
Classifier: Topic :: Software Development :: Libraries :: Application Frameworks
Requires-Python: >=3.5
License-File: LICENSE.md
